setup.py
funniest_test/__init__.py
funniest_test.egg-info/PKG-INFO
funniest_test.egg-info/SOURCES.txt
funniest_test.egg-info/dependency_links.txt
funniest_test.egg-info/not-zip-safe
funniest_test.egg-info/top_level.txt