Metadata-Version: 1.0
Name: funniest-test
Version: 0.1
Summary: Learning Python Packaging :) - go your way weary traveller, this be not your destination
Home-page: http://pypi.python.org/pypi/funniest_test/0.1
Author: Abhishek Ghose
Author-email: abhishek.ghose.82@gmail.com
License: MIT
Platform: UNKNOWN
